nosj.py
nosj-0.1.3.dist-info/licenses/LICENSE.txt
nosj-0.1.3.dist-info/METADATA
nosj-0.1.3.dist-info/WHEEL
nosj-0.1.3.dist-info/top_level.txt
nosj-0.1.3.dist-info/RECORD
