Metadata-Version: 2.4
Name: nosj
Version: 0.1.3
Summary: JSON encoding/decoding for Numpy arrays and scalars
Author-email: mpgriff <mpg@geo.au.dk>
Maintainer-email: mpgriff <mpg@geo.au.dk>
License: MIT License
Project-URL: Homepage, https://github.com/mpgriff/nosj
Project-URL: Repository, https://github.com/mpgriff/nosj.git
Project-URL: Issues, https://github.com/mpgriff/nosj/issues
Requires-Python: >=3.8
License-File: LICENSE.txt
Requires-Dist: json-numpy
Requires-Dist: numpy
Provides-Extra: torch
Requires-Dist: torch; extra == "torch"
Dynamic: license-file
